ipynb2rmd.py
ipynb2rmd-2.0.0.dist-info/DESCRIPTION.rst
ipynb2rmd-2.0.0.dist-info/METADATA
ipynb2rmd-2.0.0.dist-info/RECORD
ipynb2rmd-2.0.0.dist-info/WHEEL
ipynb2rmd-2.0.0.dist-info/entry_points.txt
ipynb2rmd-2.0.0.dist-info/metadata.json
ipynb2rmd-2.0.0.dist-info/pbr.json
ipynb2rmd-2.0.0.dist-info/top_level.txt
