Metadata-Version: 2.0
Name: ipynb2rmd
Version: 2.0.0
Summary: Convert IRkernel Jupyter Notebooks to R Markdown
Home-page: http://pypi.python.org/pypi/ipynb2rmd/
Author: Grant Patten
Author-email: grant@gpatten.com
License: MIT
Platform: UNKNOWN
Classifier: Programming Language :: Python :: 2
Classifier: Intended Audience :: Developers
Classifier: License :: OSI Approved :: MIT License
Classifier: Topic :: Utilities
